azure/cognitiveservices/vision/customvision/__init__.py
azure/cognitiveservices/vision/customvision/py.typed
azure/cognitiveservices/vision/customvision/version.py
azure/cognitiveservices/vision/customvision/prediction/__init__.py
azure/cognitiveservices/vision/customvision/prediction/_configuration.py
azure/cognitiveservices/vision/customvision/prediction/_custom_vision_prediction_client.py
azure/cognitiveservices/vision/customvision/prediction/version.py
azure/cognitiveservices/vision/customvision/prediction/models/__init__.py
azure/cognitiveservices/vision/customvision/prediction/models/_custom_vision_prediction_client_enums.py
azure/cognitiveservices/vision/customvision/prediction/models/_models.py
azure/cognitiveservices/vision/customvision/prediction/models/_models_py3.py
azure/cognitiveservices/vision/customvision/prediction/operations/__init__.py
azure/cognitiveservices/vision/customvision/prediction/operations/_custom_vision_prediction_client_operations.py
azure/cognitiveservices/vision/customvision/training/__init__.py
azure/cognitiveservices/vision/customvision/training/_configuration.py
azure/cognitiveservices/vision/customvision/training/_custom_vision_training_client.py
azure/cognitiveservices/vision/customvision/training/version.py
azure/cognitiveservices/vision/customvision/training/models/__init__.py
azure/cognitiveservices/vision/customvision/training/models/_custom_vision_training_client_enums.py
azure/cognitiveservices/vision/customvision/training/models/_models.py
azure/cognitiveservices/vision/customvision/training/models/_models_py3.py
azure/cognitiveservices/vision/customvision/training/operations/__init__.py
azure/cognitiveservices/vision/customvision/training/operations/_custom_vision_training_client_operations.py
azure_cognitiveservices_vision_customvision-3.1.1.dist-info/LICENSE
azure_cognitiveservices_vision_customvision-3.1.1.dist-info/METADATA
azure_cognitiveservices_vision_customvision-3.1.1.dist-info/WHEEL
azure_cognitiveservices_vision_customvision-3.1.1.dist-info/top_level.txt
azure_cognitiveservices_vision_customvision-3.1.1.dist-info/RECORD
